taar_monitor
