Metadata-Version: 1.1
Name: taar-monitor
Version: 0.0.10
Summary: TAAR Monitoring tools
Home-page: https://github.com/mozilla/taar-monitor
Author: Mozilla Corporation
Author-email: vng@mozilla.org
License: MPL 2.0
Platform: UNKNOWN
Classifier: Development Status :: 3 - Alpha
Classifier: Environment :: Web Environment :: Mozilla
Classifier: Intended Audience :: Developers
Classifier: License :: OSI Approved :: Mozilla Public License 2.0 (MPL 2.0)
Classifier: Programming Language :: Python
Classifier: Programming Language :: Python :: 3
Classifier: Programming Language :: Python :: 3.7
Classifier: Topic :: Internet :: WWW/HTTP
Classifier: Topic :: Scientific/Engineering :: Information Analysis
